setup.cfg
setup.py
pageview_client/__init__.py
pageview_client/clients.py
pageview_client/models.py
pageview_client.egg-info/PKG-INFO
pageview_client.egg-info/SOURCES.txt
pageview_client.egg-info/dependency_links.txt
pageview_client.egg-info/pbr.json
pageview_client.egg-info/requires.txt
pageview_client.egg-info/top_level.txt