Metadata-Version: 1.0
Name: pageview-client
Version: 1.0.2
Summary: clients and models for working with the pageview-* suite
Home-page: https://github.com/theonion/pageview-client
Author: Vince Forgione
Author-email: vforgione@theonion.com
License: MIT
Platform: UNKNOWN
